my_playground-0.1.8.dist-info/METADATA
my_playground-0.1.8.dist-info/WHEEL
playground/__init__.py
playground/hello.py
my_playground-0.1.8.dist-info/RECORD
